brec/dataset.py
brec/evaluator.py
brec-1.0.0.dist-info/LICENSE
brec-1.0.0.dist-info/METADATA
brec-1.0.0.dist-info/WHEEL
brec-1.0.0.dist-info/top_level.txt
brec-1.0.0.dist-info/RECORD
