Metadata-Version: 2.1
Name: brec
Version: 1.0.0
Summary: pypi distribution for BREC
Author-email: Yanbo Wang <wangyanbo@stu.pku.edu.cn>
Maintainer-email: Yanbo Wang <wangyanbo@stu.pku.edu.cn>
License: MIT License
Project-URL: Homepage, https://github.com/GraphPKU/BREC
Project-URL: Bug Reports, https://github.com/GraphPKU/BREC/issues
Project-URL: Source, https://github.com/GraphPKU/BREC
Keywords: machine learning,artificial intelligence,graph neural network,dataset,expressiveness
Classifier: Development Status :: 3 - Alpha
Classifier: Intended Audience :: Science/Research
Classifier: Topic :: Scientific/Engineering :: Artificial Intelligence
Classifier: License :: OSI Approved :: MIT License
Classifier: Programming Language :: Python :: 3
Classifier: Programming Language :: Python :: 3.7
Classifier: Programming Language :: Python :: 3.8
Classifier: Programming Language :: Python :: 3.9
Classifier: Programming Language :: Python :: 3.10
Classifier: Programming Language :: Python :: 3.11
Classifier: Programming Language :: Python :: 3 :: Only
Requires-Python: >=3.7
License-File: LICENSE
Requires-Dist: networkx
Requires-Dist: loguru
